profq_data/__init__.py
profq_data/helpers/__init__.py
profq_data/helpers/heap_calculator.py
profq_data/helpers/linked_list.py
profq_data/helpers/skiplist_linked_list.py
profq_data-1.0.1.dist-info/LICENSE
profq_data-1.0.1.dist-info/METADATA
profq_data-1.0.1.dist-info/WHEEL
profq_data-1.0.1.dist-info/top_level.txt
profq_data-1.0.1.dist-info/RECORD
