Metadata-Version: 2.1
Name: profq-data
Version: 1.0.1
Summary: A library for data structures.
Home-page: UNKNOWN
Author: ProfessorQu
License: UNKNOWN
Keywords: python,data structures,algorithms
Platform: UNKNOWN
Classifier: Development Status :: 1 - Planning
Classifier: Intended Audience :: Developers
Classifier: Programming Language :: Python :: 3
Classifier: Operating System :: Microsoft :: Windows
